kb_analysis/__init__.py
kb_analysis/__main__.py
kb_analysis/core.py
kb_analysis/core2.py
kb_analysis/utils.py
kb_analysis-1.0.0.dist-info/LICENSE
kb_analysis-1.0.0.dist-info/METADATA
kb_analysis-1.0.0.dist-info/WHEEL
kb_analysis-1.0.0.dist-info/entry_points.txt
kb_analysis-1.0.0.dist-info/top_level.txt
kb_analysis-1.0.0.dist-info/RECORD
